flyflow_client/__init__.py
flyflow_client/client.py
flyflowclient/__init__.py
flyflowclient/client.py
flyflowclient-1.14.21.dist-info/LICENSE
flyflowclient-1.14.21.dist-info/METADATA
flyflowclient-1.14.21.dist-info/WHEEL
flyflowclient-1.14.21.dist-info/top_level.txt
flyflowclient-1.14.21.dist-info/RECORD
