Metadata-Version: 2.1
Name: flyflowclient
Version: 1.14.21
Summary: A client library for the FlyFlow API
Home-page: https://github.com/flyflow-devs/flyflow-python
Author: Carl Cortright
Author-email: carl@flyflow.dev
Classifier: Programming Language :: Python :: 3
Classifier: License :: OSI Approved :: MIT License
Classifier: Operating System :: OS Independent
License-File: LICENSE
Requires-Dist: requests >=2.25.1
